add_stdio_mcp_server/__init__.py
add_stdio_mcp_server-0.1.0.dist-info/WHEEL
add_stdio_mcp_server-0.1.0.dist-info/entry_points.txt
add_stdio_mcp_server-0.1.0.dist-info/METADATA
add_stdio_mcp_server-0.1.0.dist-info/RECORD
