Metadata-Version: 2.3
Name: add-stdio-mcp-server
Version: 0.1.0
Summary: Add your description here
Author: 成对
Author-email: 成对 <1938116316@qq.com>
Requires-Dist: mcp[cli]>=1.12.3
Requires-Python: >=3.12.10
